awscli_saml/__init__.py
awscli_saml/assume_role.py
awscli_saml/main.py
awscli_saml/version.py
awscli_saml-2.0.2.dist-info/LICENSE.txt
awscli_saml-2.0.2.dist-info/METADATA
awscli_saml-2.0.2.dist-info/WHEEL
awscli_saml-2.0.2.dist-info/entry_points.txt
awscli_saml-2.0.2.dist-info/top_level.txt
awscli_saml-2.0.2.dist-info/RECORD
