Metadata-Version: 2.1
Name: awscli-saml
Version: 2.0.2
Summary: Authenticate AWS CLI with SAML
Home-page: https://github.com/rivethealth/aws-saml-cli
Author: Rivet Health
Author-email: ops@rivethealth.com
License: UNKNOWN
Project-URL: Issues, https://github.com/rivethealth/aws-saml-cli/issues
Platform: UNKNOWN
Classifier: License :: OSI Approved :: MIT License
Classifier: Operating System :: OS Independent
Classifier: Programming Language :: Python
Classifier: Programming Language :: Python :: 3
Classifier: Programming Language :: Python :: 2
Requires-Dist: boto3
